pytest_super_check/__init__.py
pytest_super_check/py.typed
pytest_super_check-2.6.1.dist-info/LICENSE
pytest_super_check-2.6.1.dist-info/METADATA
pytest_super_check-2.6.1.dist-info/WHEEL
pytest_super_check-2.6.1.dist-info/entry_points.txt
pytest_super_check-2.6.1.dist-info/top_level.txt
pytest_super_check-2.6.1.dist-info/RECORD
