Metadata-Version: 2.1
Name: pytest-super-check
Version: 2.6.1
Summary: Pytest plugin to check your TestCase classes call super in setUp, tearDown, etc.
Home-page: https://github.com/adamchainz/pytest-super-check
Author: Adam Johnson
Author-email: me@adamj.eu
License: MIT
Project-URL: Changelog, https://github.com/adamchainz/pytest-super-check/blob/main/HISTORY.rst
Project-URL: Twitter, https://twitter.com/adamchainz
Keywords: pytest,super,unittest,testcase
Classifier: Development Status :: 7 - Inactive
Classifier: Framework :: Pytest
Classifier: Intended Audience :: Developers
Classifier: License :: OSI Approved :: MIT License
Classifier: Natural Language :: English
Classifier: Programming Language :: Python :: 3 :: Only
Classifier: Programming Language :: Python :: 3
Classifier: Programming Language :: Python :: 3.7
Classifier: Programming Language :: Python :: 3.8
Classifier: Programming Language :: Python :: 3.9
Classifier: Programming Language :: Python :: 3.10
Classifier: Programming Language :: Python :: 3.11
Classifier: Typing :: Typed
Requires-Python: >=3.7
License-File: LICENSE
Requires-Dist: pytest
